pycounts_Anthea/__init__.py
pycounts_Anthea/plotting.py
pycounts_Anthea/pycounts_Anthea.py
pycounts_anthea-0.1.0.dist-info/LICENSE
pycounts_anthea-0.1.0.dist-info/WHEEL
pycounts_anthea-0.1.0.dist-info/METADATA
pycounts_anthea-0.1.0.dist-info/RECORD
